Compare_SQL_RedShift.py
DaskUtil.py
MasterClass.py
reportFile.html
report_attachment.html
report_text.html
Compare_SQL_RedShift307_Updated-0.1.4.dist-info/LICENSE.txt
Compare_SQL_RedShift307_Updated-0.1.4.dist-info/METADATA
Compare_SQL_RedShift307_Updated-0.1.4.dist-info/WHEEL
Compare_SQL_RedShift307_Updated-0.1.4.dist-info/top_level.txt
Compare_SQL_RedShift307_Updated-0.1.4.dist-info/RECORD
