Metadata-Version: 2.1
Name: Compare-SQL-RedShift307-Updated
Version: 0.1.4
Summary: Say Hello....
Home-page: https://github.com/rajnish307/Test_upload_with_multipl-e_files
Author: Rajnish
Author-email: rajnishkumar307@gmail.com
License: UNKNOWN
Platform: UNKNOWN
Classifier: Programming Language :: Python :: 3
Classifier: Programming Language :: Python :: 3.6
Classifier: Programming Language :: Python :: 3.7
Classifier: License :: OSI Approved :: GNU General Public License v2 or later (GPLv2+)
Classifier: Operating System :: OS Independent
Provides-Extra: dev
Requires-Dist: pytest (>=3.7) ; extra == 'dev'
